[
	{
		"profileImg": "images/profile-img.jpg",
		"feedId": "Connor Underwood",
        "imgContent": "images/profile-img.jpg",
		"likesCount": ["Larissa Dominguez", "Tallulah Todd", "Dexter Coleman"],
		"textContent": "Nullam enim. Sed nulla ante, iaculis nec, eleifend non, dapibus rutrum, justo. Praesent luctus. Curabitur egestas nunc",
		"comment": [
            {
                "commentId": "Larissa Dominguez",
                "commentText": "nulla. In tincidunt congue turpis. In condimentum."
            },
            {
                "commentId": "Tallulah Todd",
                "commentText": "id, erat."
            },
            {
                "commentId": "Cheryl Buchanan",
                "commentText": "luctus vulputate, nisi sem"
            },
            {
                "commentId": "Jonah Moore",
                "commentText": "Quisque libero lacus, varius et, euismod"
            },
            {
                "commentId": "Dexter Coleman",
                "commentText": "morbi tristique senectus"
            }
        ]
	},
	{
		"profileImg": "images/profile-img2.jpg",
		"feedId": "Hollee Callahan",
        "imgContent": "images/profile-img2.jpg",
		"likesCount": ["Jonah Moore", "Hyacinth Petersen", "Larissa Dominguez", "Tallulah Todd", "Dexter Coleman"],
		"textContent": "et malesuada",
		"comment": [{
            "commentId": "Cheryl Buchanan",
            "commentText": "luctus vulputate, nisi sem"
        },
        {
            "commentId": "Jonah Moore",
            "commentText": "Quisque libero lacus, varius et, euismod"
        }
        ]
	},
	{
		"profileImg": "images/profile-img3.jpg",
		"feedId": "Stella Banks",
        "imgContent": "images/profile-img3.jpg",
		"likesCount": ["Dexter Coleman", "Jonah Moore", "Larissa Dominguez", "Tallulah Todd", "Dexter Coleman"],
		"textContent": "Maecenas mi felis, adipiscing fringilla, porttitor vulputate, posuere vulputate, lacus. Cras interdum. Nunc sollicitudin commodo ipsum. Suspendisse non leo. Vivamus nibh dolor,",
		"comment": [            {
            "commentId": "Dexter Coleman",
            "commentText": "morbi tristique senectus"
        }]
	},
	{
		"profileImg": "images/profile-img4.jpg",
		"feedId": "Alden Garza",
        "imgContent": "images/profile-img4.jpg",
		"likesCount": ["Remedios Sloan", "Hyacinth Petersen", "Russell Sandoval", "Dexter Coleman", "Jonah Moore", "Larissa Dominguez", "Tallulah Todd", "Dexter Coleman"],
		"textContent": "a felis ullamcorper viverra. Maecenas iaculis",
		"comment": [
            {
                "commentId": "Hyacinth Petersen",
                "commentText": "Aliquam tincidunt, nunc ac"
            },
            {
                "commentId": "Remedios Sloan",
                "commentText": "Cras dolor dolor, tempus non, lacinia at,"
            },
            {
                "commentId": "Amanda Hampton",
                "commentText": "nisi sem"
            },
            {
                "commentId": "Dillon Joyner",
                "commentText": "dapibus gravida. Aliquam tincidunt, nunc ac"
            },
            {
                "commentId": "Hollee Anderson",
                "commentText": "elit pede, malesuada"
            }
        ]
	},
	{
		"profileImg": "images/profile-img5.jpg",
		"feedId": "Fulton Luna",
        "imgContent": "images/profile-img5.jpg",
		"likesCount": ["Russell Sandoval", "Dexter Coleman", "Jonah Moore", "Larissa Dominguez", "Tallulah Todd", "Dexter Coleman"],
		"textContent": "mauris ut mi. Duis risus odio, auctor vitae, aliquet nec, imperdiet nec, leo. Morbi neque tellus, imperdiet non, vestibulum",
		"comment": [
            {
                "commentId": "Lani Tran",
                "commentText": "sit amet luctus vulputate, nisi"
            },
            {
                "commentId": "Russell Sandoval",
                "commentText": "nisl. Nulla eu neque pellentesque massa"
            },
            {
                "commentId": "Audra Jefferson",
                "commentText": "bibendum sed, est. Nunc laoreet"
            }
        ]
	}
]
